[
    {
      "href": "becas-escritorio",
      "title": "Escritorio",
      "icon": "mdi-home",
      "params": {},
      "permission": "show-escritorio"
    },
    {
      "href": "becas-universidades",
      "title": "Universidades",
      "icon": "mdi-handshake",
      "params": {},
      "permission": "show-universidades"
    }, {
      "href": "becas-seguimiento",
      "title": "Seguimiento Beca",
      "icon": "mdi-layers-search",
      "permission": "show-seguimiento-beca",
      "params": {}
    }, {
      "href": "Ajustes",
      "title": "Ajustes",
      "icon": "mdi-cog",
      "permission": "show-ajustes",
      "group": [
        {
          "href": "becas-convocatorias",
          "title": "Convocatorias",
          "icon": "mdi-calendar-multiple-check",
          "permission": "show-ajustes",
          "params": {}
        },
        {
          "href": "becas-usuarios",
          "title": "Usuarios",
          "icon": "mdi-account-multiple",
          "permission": "show-ajustes",
          "params": {}
        }
      ]
    }
  ]